protemp/MANIFEST_r.py
protemp/README_r.py
protemp/__init__.py
protemp/__main__.py
protemp/config_r.py
protemp/file_creator.py
protemp/helper.py
protemp/helper_r.py
protemp/init_r.py
protemp/main_r.py
protemp/p_imp1_r.py
protemp/setup_r.py
matrix_pypitmp-1.1.0.dist-info/LICENSE
matrix_pypitmp-1.1.0.dist-info/METADATA
matrix_pypitmp-1.1.0.dist-info/WHEEL
matrix_pypitmp-1.1.0.dist-info/entry_points.txt
matrix_pypitmp-1.1.0.dist-info/top_level.txt
matrix_pypitmp-1.1.0.dist-info/RECORD
