Metadata-Version: 2.1
Name: matrix-pypitmp
Version: 1.1.0
Summary: Create a template for pypi repo
Home-page: https://github.com/mohankumarpaluru/matrix-pypitmp
Author: Mohan Kumar Paluru
Author-email: trixter127@pm.me
License: MIT
Platform: UNKNOWN
Classifier: License :: OSI Approved :: MIT License
Classifier: Programming Language :: Python
Classifier: Programming Language :: Python :: 2
Classifier: Programming Language :: Python :: 3
Requires-Dist: wheel
Requires-Dist: twine
